gfap_segmenter/__init__.py
gfap_segmenter/_reader.py
gfap_segmenter/_version.py
gfap_segmenter/_widget.py
gfap_segmenter/_writer.py
gfap_segmenter/background.py
gfap_segmenter/data_utils.py
gfap_segmenter/model_manager.py
gfap_segmenter/napari.yaml
gfap_segmenter/training.py
gfap_segmenter-1.0.0.dist-info/licenses/LICENSE
gfap_segmenter-1.0.0.dist-info/METADATA
gfap_segmenter-1.0.0.dist-info/WHEEL
gfap_segmenter-1.0.0.dist-info/entry_points.txt
gfap_segmenter-1.0.0.dist-info/top_level.txt
gfap_segmenter-1.0.0.dist-info/RECORD
