Metadata-Version: 2.4
Name: gfap-segmenter
Version: 1.0.0
Summary: A Bachelor Thesis project to allow Segmentation of Astrocytes on GFAP Staining using Machine Learning in napari
Author: Lennart Kowitz
Author-email: lennart.kowitz@isas.de
License: 
Project-URL: Bug Tracker, https://github.com/MMV-Lab/gfap-segmenter/issues
Project-URL: Documentation, https://github.com/MMV-Lab/gfap-segmenter#README.md
Project-URL: Source Code, https://github.com/MMV-Lab/gfap-segmenter
Project-URL: User Support, https://github.com/MMV-Lab/gfap-segmenter/issues
Classifier: Development Status :: 2 - Pre-Alpha
Classifier: Framework :: napari
Classifier: Intended Audience :: Developers
Classifier: License :: OSI Approved :: BSD License
Classifier: Operating System :: OS Independent
Classifier: Programming Language :: Python
Classifier: Programming Language :: Python :: 3
Classifier: Programming Language :: Python :: 3 :: Only
Classifier: Programming Language :: Python :: 3.10
Classifier: Programming Language :: Python :: 3.11
Classifier: Programming Language :: Python :: 3.12
Classifier: Programming Language :: Python :: 3.13
Classifier: Topic :: Scientific/Engineering :: Image Processing
Requires-Python: >=3.10
License-File: LICENSE
Requires-Dist: numpy
Requires-Dist: qtpy
Requires-Dist: scikit-image
Requires-Dist: tifffile
Requires-Dist: bioio
Requires-Dist: bioio-czi
Requires-Dist: torch>=2.0.0
Requires-Dist: onnx
Requires-Dist: onnxruntime
Requires-Dist: tqdm
Provides-Extra: all
Requires-Dist: napari[all]; extra == "all"
Dynamic: license-file
